MANIFEST.in
README.txt
setup.py
collective/__init__.py
collective.powertoken.core.egg-info/PKG-INFO
collective.powertoken.core.egg-info/SOURCES.txt
collective.powertoken.core.egg-info/dependency_links.txt
collective.powertoken.core.egg-info/entry_points.txt
collective.powertoken.core.egg-info/namespace_packages.txt
collective.powertoken.core.egg-info/not-zip-safe
collective.powertoken.core.egg-info/requires.txt
collective.powertoken.core.egg-info/top_level.txt
collective/powertoken/__init__.py
collective/powertoken/core/__init__.py
collective/powertoken/core/config.py
collective/powertoken/core/configure.zcml
collective/powertoken/core/exceptions.py
collective/powertoken/core/interfaces.py
collective/powertoken/core/tokenaction.py
collective/powertoken/core/utility.py
collective/powertoken/core/browser/__init__.py
collective/powertoken/core/browser/configure.zcml
collective/powertoken/core/browser/consume_token.py
collective/powertoken/core/tests/__init__.py
collective/powertoken/core/tests/base.py
collective/powertoken/core/tests/test_utility.py
collective/powertoken/core/tests/test_view.py
docs/HISTORY.txt
docs/INSTALL.txt
docs/KNOW-ACTION-PROVIDERS.txt
docs/LICENSE.GPL
docs/LICENSE.txt