Metadata-Version: 1.0
Name: collective.powertoken.core
Version: 0.1.0
Summary: A mechanism for bypass Plone security, accessing specific URLs while giving a secret token (core package)
Home-page: http://plone.org/collective.powertoken.core
Author: RedTurtle Technology
Author-email: sviluppoplone@redturtle.it
License: GPL
Keywords: plone security token plonegov
Platform: UNKNOWN
Classifier: Framework :: Plone
Classifier: Framework :: Plone :: 3.3
Classifier: Framework :: Plone :: 4.0
Classifier: Framework :: Plone :: 4.1
Classifier: Framework :: Zope2
Classifier: Framework :: Zope3
Classifier: Development Status :: 3 - Alpha
Classifier: Intended Audience :: Developers
Classifier: Programming Language :: Python
